loki_assistant/__init__.py
loki_assistant/loki_assistant.py
loki_assistant-0.0.2.dist-info/LICENSE.txt
loki_assistant-0.0.2.dist-info/METADATA
loki_assistant-0.0.2.dist-info/WHEEL
loki_assistant-0.0.2.dist-info/top_level.txt
loki_assistant-0.0.2.dist-info/RECORD
