Metadata-Version: 2.1
Name: loki-assistant
Version: 0.0.2
Summary: The LokiAssistant lib is a small tool to push logging to Loki server.
Home-page: https://github.com/grobbles/LokiAssistant
Author: Uwe Roder
Author-email: uweroder@gmail.com
License: MIT
Keywords: loki_assistant,Loki,Assistant,Grafana
Classifier: Development Status :: 3 - Alpha
Classifier: License :: OSI Approved :: MIT License
Classifier: Intended Audience :: Developers
Classifier: Topic :: Communications
Classifier: Topic :: Utilities
Classifier: Programming Language :: Python
Classifier: Programming Language :: Python :: 3.7
Classifier: Programming Language :: Python :: 3.8
Classifier: Programming Language :: Python :: 3.9
Classifier: Programming Language :: Python :: 3.10
Requires-Python: >=3.7
License-File: LICENSE.txt
Requires-Dist: requests
